appian_locust/__init__.py
appian_locust/_actions.py
appian_locust/_admin.py
appian_locust/_base.py
appian_locust/_control_panel_workspace.py
appian_locust/_data_fabric.py
appian_locust/_design.py
appian_locust/_feature_toggle_helper.py
appian_locust/_grid_interactor.py
appian_locust/_interactor.py
appian_locust/_locust_error_handler.py
appian_locust/_news.py
appian_locust/_portals.py
appian_locust/_rdo_interactor.py
appian_locust/_records.py
appian_locust/_records_helper.py
appian_locust/_reports.py
appian_locust/_save_request_builder.py
appian_locust/_sites.py
appian_locust/_task_opener.py
appian_locust/_tasks.py
appian_locust/_ui_reconciler.py
appian_locust/appian_client.py
appian_locust/appian_task_set.py
appian_locust/client_mode.py
appian_locust/feature_flag.py
appian_locust/system_operator.py
appian_locust/visitor.py
appian_locust/exceptions/__init__.py
appian_locust/exceptions/exceptions.py
appian_locust/info/__init__.py
appian_locust/info/actions_info.py
appian_locust/info/news_info.py
appian_locust/info/records_info.py
appian_locust/info/reports_info.py
appian_locust/info/sites_info.py
appian_locust/info/tasks_info.py
appian_locust/objects/__init__.py
appian_locust/objects/ai_skill.py
appian_locust/objects/ai_skill_type.py
appian_locust/objects/application.py
appian_locust/objects/design_object.py
appian_locust/objects/page.py
appian_locust/objects/site.py
appian_locust/uiform/InterfaceDesignerUiForm.py
appian_locust/uiform/__init__.py
appian_locust/uiform/ai_skill_uiform.py
appian_locust/uiform/application_uiform.py
appian_locust/uiform/design_object_uiform.py
appian_locust/uiform/design_uiform.py
appian_locust/uiform/record_list_uiform.py
appian_locust/uiform/record_uiform.py
appian_locust/uiform/uiform.py
appian_locust/utilities/__init__.py
appian_locust/utilities/credentials.py
appian_locust/utilities/helper.py
appian_locust/utilities/loadDriverUtils.py
appian_locust/utilities/logger.py
appian_locust/utilities/url_provider.py
appian_locust-2.27.6.dist-info/licenses/LICENSE
appian_locust-2.27.6.dist-info/METADATA
appian_locust-2.27.6.dist-info/WHEEL
appian_locust-2.27.6.dist-info/top_level.txt
appian_locust-2.27.6.dist-info/RECORD
