Metadata-Version: 2.4
Name: appian-locust
Version: 2.27.6
Summary: Tools and functions to make testing Appian with Locust easier
Home-page: https://gitlab.com/appian-oss/appian-locust
Author: Appian Performance & Reliability Engineering Squad
License: Apache 2.0
Classifier: Programming Language :: Python :: 3.7
Classifier: Programming Language :: Python :: 3.8
Classifier: Programming Language :: Python :: 3.9
Classifier: Intended Audience :: Developers
Classifier: Development Status :: 5 - Production/Stable
License-File: LICENSE
Requires-Dist: locust>=2.40.2
Requires-Dist: uritemplate>=4.1.1
Requires-Dist: sseclient-py>=1.8.0
Dynamic: author
Dynamic: description
Dynamic: description-content-type
Dynamic: home-page
Dynamic: license
Dynamic: license-file
Dynamic: requires-dist
Dynamic: summary
